pieorg/app.py
pieorg-1.0.2.dist-info/METADATA
pieorg-1.0.2.dist-info/WHEEL
pieorg-1.0.2.dist-info/entry_points.txt
pieorg-1.0.2.dist-info/top_level.txt
pieorg-1.0.2.dist-info/RECORD
