Metadata-Version: 2.1
Name: pieorg
Version: 1.0.2
Summary: A Python CLI app to organise every story you read on the internet.
Home-page: https://github.com/yashprakash13/PieOrg
Author: Yash Prakash
Author-email: yashprakash13@gmail.com
License: MIT
Platform: UNKNOWN
Requires-Dist: click
Requires-Dist: art
